starparse/__init__.py
starparse/config.py
starparse/pack.py
starparse/unpack.py
starparse/util.py
tests/__init__.py
tests/test_e2e.py
tests/test_pack_unpack.py
tests/ci_players/__init__.py
starparse-0.1.1.dist-info/LICENSE
starparse-0.1.1.dist-info/METADATA
starparse-0.1.1.dist-info/WHEEL
starparse-0.1.1.dist-info/top_level.txt
starparse-0.1.1.dist-info/RECORD
