Metadata-Version: 2.1
Name: starparse
Version: 0.1.1
Summary: Starbound save game parser
Home-page: https://github.com/buhanec/starparse
Author: Alen Buhanec
Author-email: <alen.buhanec@gmail.com>
License: MIT
Platform: UNKNOWN
Classifier: Topic :: Utilities
Classifier: Development Status :: 3 - Alpha
Classifier: Programming Language :: Python :: 3
Classifier: Programming Language :: Python :: 3.7
Classifier: Programming Language :: Python :: 3.8
Classifier: Programming Language :: Python :: 3.9
Classifier: License :: OSI Approved :: MIT License
Classifier: Operating System :: OS Independent
Classifier: Typing :: Typed
